calc_package/__init__.py
calc_package/mycounter.py
calc_package-0.1.0.dist-info/LICENSE
calc_package-0.1.0.dist-info/WHEEL
calc_package-0.1.0.dist-info/METADATA
calc_package-0.1.0.dist-info/RECORD
