Metadata-Version: 2.1
Name: calc_package
Version: 0.1.0
Summary: A package for performing a calculations
Author-email: Shari_Yo <vykintas.palskys@gmail.com>
Classifier: License :: OSI Approved :: MIT License
